ggd/__ggd.py
ggd/__init__.py
ggd/config/__config.py
ggd/config/__init__.py
ggd/exceptions/__exception.py
ggd/exceptions/__init__.py
ggd/match/__init__.py
ggd/match/__match.py
ggd-0.3.0.dist-info/METADATA
ggd-0.3.0.dist-info/WHEEL
ggd-0.3.0.dist-info/top_level.txt
ggd-0.3.0.dist-info/RECORD
